AUTHORS.rst
HISTORY.rst
LICENSE
MANIFEST.in
README.rst
setup.cfg
setup.py
hein/__init__.py
hein/_version.py
hein/core.py
hein/socreceiver.py
hein/soctransmitter.py
hein.egg-info/PKG-INFO
hein.egg-info/SOURCES.txt
hein.egg-info/dependency_links.txt
hein.egg-info/requires.txt
hein.egg-info/top_level.txt