Metadata-Version: 1.1
Name: hein
Version: 0.2.3
Summary: Advanced Subscriber-Publisher Socket Communication
Home-page: https://github.com/ceyzeriat/hein/
Author: Guillaume Schworer
Author-email: guillaume.schworer@gmail.com
License: GNU General Public License v3 or later (GPLv3+)
Download-URL: https://github.com/ceyzeriat/hein/tree/master/dist
Keywords: socket,communication,publisher,transmitter,emitter,receiver,subscriber,process,inter,interprocess
Platform: UNKNOWN
Classifier: Development Status :: 4 - Beta
Classifier: Environment :: Console
Classifier: Intended Audience :: Developers
Classifier: Intended Audience :: Education
Classifier: Intended Audience :: Science/Research
Classifier: License :: OSI Approved :: GNU General Public License v3 or later (GPLv3+)
Classifier: Operating System :: OS Independent
Classifier: Programming Language :: Python
Classifier: Topic :: Documentation :: Sphinx
